Workbook

Sheet Overview
A1: PROJECT ATLAS | Stakeholder Management
A3: Version 1.0 • Synthetic example • M1 (Initiation)
A5: STAKEHOLDERS | B5: COUNT | D5: POWER–INTEREST RESPONSE | E5: COUNT | F5: OWNER
A6: Identified roles | B6: =COUNTA('Stakeholder Register'!A7:A24) -> 18 | D6: Manage closely | E6: =COUNTIF('Stakeholder Register'!H7:H24,D6) -> 9 | F6: Named engagement owner in register
A7: Manage closely | B7: =COUNTIF('Stakeholder Register'!H7:H24,"Manage closely") -> 9 | D7: Keep satisfied | E7: =COUNTIF('Stakeholder Register'!H7:H24,D7) -> 3 | F7: Named engagement owner in register
A8: Open engagement gaps | B8: =COUNTIF('Stakeholder Register'!N7:N24,1) -> 17 | D8: Keep informed | E8: =COUNTIF('Stakeholder Register'!H7:H24,D8) -> 5 | F8: Named engagement owner in register
D9: Monitor | E9: =COUNTIF('Stakeholder Register'!H7:H24,D9) -> 1 | F9: Named engagement owner in register
A12: HOW TO USE
A13: 1. Review Stakeholder Register and validate role, power, interest, engagement state and owner.
A14: 2. Use priority categories to allocate engagement effort; high power + high interest = manage closely.
A15: 3. Review engagement gaps and execute the actions in Engagement Plan.
A16: 4. Reassess at major gates and after material scope, organization, or risk changes.
A17: 5. Public portfolio version: role-based and synthetic. Real engagement assessments are restricted.

Sheet Stakeholder Register
A1: PROJECT ATLAS | Stakeholder Register
A3: Simulation • M1, after charter approval • Version 1.0 • All roles and assessments synthetic
A4: Public, role-based portfolio demonstration only. Do not add real names, contacts, or confidential stakeholder assessments.
A6: ID | B6: Stakeholder / Role | C6: Group | D6: Region | E6: Project interest / responsibility | F6: Power (1–5) | G6: Interest (1–5) | H6: Priority | I6: Current engagement | J6: Target engagement | K6: Engagement owner | L6: Principal concern | M6: Stage-gate / decision touchpoint | N6: Engagement gap
A7: ST-01 | B7: Executive Sponsor | C7: Executive | D7: Global | E7: Strategic outcomes, funding and major decisions | F7: 5 | G7: 5 | H7: =IF(AND(F7>=4,G7>=4),"Manage closely",IF(F7>=4,"Keep satisfied",IF(G7>=4,"Keep informed","Monitor"))) -> Manage closely | I7: Supportive | J7: Leading | K7: Project Manager | L7: Benefits realization; cost and schedule exposure | M7: Charter, Steering Committee, investment and go/no-go | N7: =IF(I7=J7,0,1) -> 1
A8: ST-02 | B8: Business Owner | C8: Business | D8: US / UK | E8: Business outcomes, requirements, UAT and benefits ownership | F8: 5 | G8: 5 | H8: =IF(AND(F8>=4,G8>=4),"Manage closely",IF(F8>=4,"Keep satisfied",IF(G8>=4,"Keep informed","Monitor"))) -> Manage closely | I8: Supportive | J8: Leading | K8: Project Manager | L8: Workflow continuity and business acceptance | M8: Requirements baseline, UAT and benefits handover | N8: =IF(I8=J8,0,1) -> 1
A9: ST-03 | B9: Technology Director | C9: Technology | D9: Global | E9: Technology capacity, technical direction and readiness | F9: 5 | G9: 4 | H9: =IF(AND(F9>=4,G9>=4),"Manage closely",IF(F9>=4,"Keep satisfied",IF(G9>=4,"Keep informed","Monitor"))) -> Manage closely | I9: Supportive | J9: Leading | K9: Project Manager | L9: Solution supportability and resource conflicts | M9: Architecture/design, capacity and release readiness | N9: =IF(I9=J9,0,1) -> 1
A10: ST-04 | B10: Quality & Compliance Lead | C10: Compliance | D10: Global | E10: Validation strategy, traceability and regulated controls | F10: 5 | G10: 5 | H10: =IF(AND(F10>=4,G10>=4),"Manage closely",IF(F10>=4,"Keep satisfied",IF(G10>=4,"Keep informed","Monitor"))) -> Manage closely | I10: Neutral | J10: Leading | K10: Validation & QA Lead | L10: Validation evidence and compliant release | M10: Validation strategy, validation exit and release sign-off | N10: =IF(I10=J10,0,1) -> 1
A11: ST-05 | B11: Project Manager | C11: PMO | D11: India / Global | E11: Integrated plan, cost, RAID, change and coordination | F11: 4 | G11: 5 | H11: =IF(AND(F11>=4,G11>=4),"Manage closely",IF(F11>=4,"Keep satisfied",IF(G11>=4,"Keep informed","Monitor"))) -> Manage closely | I11: Leading | J11: Leading | K11: Executive Sponsor | L11: Timely decisions and balanced delivery constraints | M11: All stage-gate recommendations and governance | N11: =IF(I11=J11,0,1) -> 0
A12: ST-06 | B12: Solution Architect | C12: Technology | D12: India | E12: Design integrity and cross-system architecture | F12: 4 | G12: 5 | H12: =IF(AND(F12>=4,G12>=4),"Manage closely",IF(F12>=4,"Keep satisfied",IF(G12>=4,"Keep informed","Monitor"))) -> Manage closely | I12: Supportive | J12: Leading | K12: Project Manager | L12: Architecture fit, nonfunctional requirements | M12: Design approval and production readiness | N12: =IF(I12=J12,0,1) -> 1
A13: ST-07 | B13: Application Development Lead | C13: Delivery | D13: India | E13: Application build, technical quality and fixes | F13: 3 | G13: 5 | H13: =IF(AND(F13>=4,G13>=4),"Manage closely",IF(F13>=4,"Keep satisfied",IF(G13>=4,"Keep informed","Monitor"))) -> Keep informed | I13: Supportive | J13: Leading | K13: Project Manager | L13: Build capacity and requirements stability | M13: Build completion and defect triage | N13: =IF(I13=J13,0,1) -> 1
A14: ST-08 | B14: Integration & Migration Lead | C14: Delivery | D14: India | E14: Four interfaces, mapping and migration quality | F14: 4 | G14: 5 | H14: =IF(AND(F14>=4,G14>=4),"Manage closely",IF(F14>=4,"Keep satisfied",IF(G14>=4,"Keep informed","Monitor"))) -> Manage closely | I14: Supportive | J14: Leading | K14: Project Manager | L14: Interface dependencies and source-data quality | M14: Integration/SIT exit and migration rehearsal | N14: =IF(I14=J14,0,1) -> 1
A15: ST-09 | B15: Validation & QA Lead | C15: Quality | D15: India | E15: Test execution, defects and requirements traceability | F15: 4 | G15: 5 | H15: =IF(AND(F15>=4,G15>=4),"Manage closely",IF(F15>=4,"Keep satisfied",IF(G15>=4,"Keep informed","Monitor"))) -> Manage closely | I15: Supportive | J15: Leading | K15: Project Manager | L15: Test coverage, defect closure and evidence | M15: SIT exit, validation exit and release readiness | N15: =IF(I15=J15,0,1) -> 1
A16: ST-10 | B16: Business SME / UAT Lead | C16: Business | D16: UK | E16: Scenario validation and representative user acceptance | F16: 3 | G16: 5 | H16: =IF(AND(F16>=4,G16>=4),"Manage closely",IF(F16>=4,"Keep satisfied",IF(G16>=4,"Keep informed","Monitor"))) -> Keep informed | I16: Neutral | J16: Supportive | K16: Business Owner | L16: UAT time allocation and critical workflows | M16: Requirements workshops and UAT sign-off | N16: =IF(I16=J16,0,1) -> 1
A17: ST-11 | B17: Information Security Lead | C17: Security | D17: Global | E17: Security assessment and release controls | F17: 5 | G17: 3 | H17: =IF(AND(F17>=4,G17>=4),"Manage closely",IF(F17>=4,"Keep satisfied",IF(G17>=4,"Keep informed","Monitor"))) -> Keep satisfied | I17: Neutral | J17: Supportive | K17: Technology Director | L17: Vulnerabilities, access and security findings | M17: Security assessment and readiness sign-off | N17: =IF(I17=J17,0,1) -> 1
A18: ST-12 | B18: Operations & Service Transition Lead | C18: Operations | D18: India / UK | E18: Monitoring, runbooks, support readiness and handover | F18: 4 | G18: 4 | H18: =IF(AND(F18>=4,G18>=4),"Manage closely",IF(F18>=4,"Keep satisfied",IF(G18>=4,"Keep informed","Monitor"))) -> Manage closely | I18: Neutral | J18: Supportive | K18: Technology Director | L18: Support workload and incomplete handover | M18: Cutover, go-live readiness and hypercare exit | N18: =IF(I18=J18,0,1) -> 1
... A24: ST-18 | B24: Data Governance / Privacy Lead | C24: Data Governance | D24: Global | E24: Data use, retention and migration governance | F24: 5 | G24: 3 | H24: =IF(AND(F24>=4,G24>=4),"Manage closely",IF(F24>=4,"Keep satisfied",IF(G24>=4,"Keep informed","Monitor"))) -> Keep satisfied | I24: Neutral | J24: Supportive | K24: Technology Director | L24: Data minimization, reconciliation and retention | M24: Migration design and data-governance sign-off | N24: =IF(I24=J24,0,1) -> 1

Sheet Engagement Plan
A1: PROJECT ATLAS | Stakeholder Engagement Plan
A3: Engagement actions correspond to IDs in the Stakeholder Register; cadence is the proposed project approach.
A5: ID | B5: Stakeholder / Role | C5: Priority | D5: Engagement approach / information | E5: Channel / evidence | F5: Cadence | G5: Escalation trigger | H5: Immediate action
A6: ST-01 | B6: ='Stakeholder Register'!B7 -> Executive Sponsor | C6: ='Stakeholder Register'!H7 -> Manage closely | D6: Decision-focused executive brief | E6: Steering pack + one-page exception summary | F6: Monthly; urgent exceptions same day | G6: Cost/schedule forecast outside tolerance; blocked gate | H6: Confirm benefit owner and funding guardrails
A7: ST-02 | B7: ='Stakeholder Register'!B8 -> Business Owner | C7: ='Stakeholder Register'!H8 -> Manage closely | D7: Joint outcomes and acceptance reviews | E7: Business demos + requirements/UAT decisions | F7: Fortnightly; at acceptance gates | G7: Unresolved high-impact process or acceptance issue | H7: Agree measurable UAT criteria and benefits handover
A8: ST-03 | B8: ='Stakeholder Register'!B9 -> Technology Director | C8: ='Stakeholder Register'!H9 -> Manage closely | D8: Technical and resource decision forum | E8: Architecture/dependency review | F8: Weekly during design/build | G8: Critical specialist shortfall or design conflict | H8: Confirm technical capacity and architecture approval path
A9: ST-04 | B9: ='Stakeholder Register'!B10 -> Quality & Compliance Lead | C9: ='Stakeholder Register'!H10 -> Manage closely | D9: Early validation co-design | E9: Requirements traceability + validation evidence review | F9: Weekly; each formal gate | G9: Validation gap or missing mandatory evidence | H9: Agree validation evidence checklist before design freeze
A10: ST-05 | B10: ='Stakeholder Register'!B11 -> Project Manager | C10: ='Stakeholder Register'!H11 -> Manage closely | D10: Integrated delivery and control | E10: Workstream plans, RAID, EVM and action log | F10: Daily/weekly; monthly steering | G10: Cross-workstream blockage or forecast tolerance breach | H10: Keep baseline and decision log current
A11: ST-06 | B11: ='Stakeholder Register'!B12 -> Solution Architect | C11: ='Stakeholder Register'!H12 -> Manage closely | D11: Architecture working sessions | E11: Design decisions and integration diagrams | F11: Weekly through design/build | G11: Nonfunctional requirement or design exception | H11: Baseline solution architecture and design assumptions
A12: ST-07 | B12: ='Stakeholder Register'!B13 -> Application Development Lead | C12: ='Stakeholder Register'!H13 -> Keep informed | D12: Build planning and blocker removal | E12: Work-package board + defect review | F12: Twice weekly during build | G12: Critical-path slippage or unresolved blocker | H12: Confirm build estimates and handoffs to SIT
A13: ST-08 | B13: ='Stakeholder Register'!B14 -> Integration & Migration Lead | C13: ='Stakeholder Register'!H14 -> Manage closely | D13: Interface and migration dependency reviews | E13: Interface tracker + reconciliation samples | F13: Weekly; more often at SIT/cutover | G13: Missing test endpoint, extract or poor migration quality | H13: Secure interface commitments and migration rehearsal
A14: ST-09 | B14: ='Stakeholder Register'!B15 -> Validation & QA Lead | C14: ='Stakeholder Register'!H15 -> Manage closely | D14: Test/validation controls and reporting | E14: RTM, test summary and defects | F14: Weekly; daily near quality gates | G14: Severity-1 defect or mandatory test evidence missing | H14: Agree exit criteria and evidence ownership
A15: ST-10 | B15: ='Stakeholder Register'!B16 -> Business SME / UAT Lead | C15: ='Stakeholder Register'!H16 -> Keep informed | D15: Time-boxed business walkthroughs | E15: Scenario reviews + UAT progress summary | F15: Fortnightly; daily during UAT | G15: Business users unavailable or acceptance blocked | H15: Book UAT participants and confirm representative scenarios
A16: ST-11 | B16: ='Stakeholder Register'!B17 -> Information Security Lead | C16: ='Stakeholder Register'!H17 -> Keep satisfied | D16: Targeted security consultations | E16: Threat/risk assessment + finding register | F16: At design and pre-go-live; exceptions as needed | G16: Critical security finding or late control change | H16: Confirm security assessment window and sign-off criteria
A17: ST-12 | B17: ='Stakeholder Register'!B18 -> Operations & Service Transition Lead | C17: ='Stakeholder Register'!H18 -> Manage closely | D17: Operational readiness co-planning | E17: Runbook, monitoring and handover checklist | F17: Fortnightly from build; daily at cutover | G17: Missing runbook or unresolved support ownership | H17: Agree support model, transition criteria and hypercare rota
... A23: ST-18 | B23: ='Stakeholder Register'!B24 -> Data Governance / Privacy Lead | C23: ='Stakeholder Register'!H24 -> Keep satisfied | D23: Early data-control assessment | E23: Data inventory, mapping and retention decisions | F23: At migration design and cutover gates | G23: Privacy concern or reconciliation failure | H23: Confirm sensitive data controls and retention rules

Sheet Assessment Guide
A1: PROJECT ATLAS | Assessment Guide
A3: Qualitative ratings are simulated; decision rights are defined separately in Governance-Model.md.
A5: DIMENSION | B5: VALUE | C5: GUIDANCE
A6: Power | B6: 1 | C6: Minimal ability to alter outcomes or release decisions
A7: Power | B7: 3 | C7: Can materially influence a workstream or delivery decision
A8: Power | B8: 5 | C8: Formal authority over funding, acceptance, compliance, or gate outcome
A9: Interest | B9: 1 | C9: Limited involvement or impact
A10: Interest | B10: 3 | C10: Periodic engagement or discrete gate concern
A11: Interest | B11: 5 | C11: Direct, ongoing impact on project delivery or outcomes
A12: Engagement | B12: Unaware | C12: Not yet aware of the project or its implications
A13: Engagement | B13: Resistant | C13: Opposed to the change or proposed approach
A14: Engagement | B14: Neutral | C14: Aware, not yet actively supporting
A15: Engagement | B15: Supportive | C15: Participates constructively
A16: Engagement | B16: Leading | C16: Actively champions or facilitates outcomes
... A23: Monitor | B23: Power ≤3, interest ≤3 | C23: Proportionate, event-driven communication
